README.rst
setup.py
recharge/__init__.py
recharge/resources.py
recharge.egg-info/PKG-INFO
recharge.egg-info/SOURCES.txt
recharge.egg-info/dependency_links.txt
recharge.egg-info/not-zip-safe
recharge.egg-info/requires.txt
recharge.egg-info/top_level.txt