Metadata-Version: 1.1
Name: recharge
Version: 1.0.0
Summary: Python API Wrapper for Recharge
Home-page: http://github.com/BuluBox/recharge-api
Author: Tobin Brown
Author-email: tobin@bulugroup.com
License: MIT
Keywords: api recharge
Platform: UNKNOWN
Classifier: Development Status :: 3 - Alpha
Classifier: Intended Audience :: Information Technology
Classifier: License :: OSI Approved :: MIT License
Classifier: Natural Language :: English
Classifier: Programming Language :: Python :: 3
Classifier: Programming Language :: Python :: 3.6
Classifier: Topic :: Software Development :: Libraries :: Python Modules
Classifier: Topic :: Software Development :: Testing
Classifier: Topic :: Utilities
